ipython_suggestions.py
super_greedy_complete.py
ipython_suggestions-1.0.3.dist-info/licenses/LICENSE.txt
ipython_suggestions-1.0.3.dist-info/METADATA
ipython_suggestions-1.0.3.dist-info/WHEEL
ipython_suggestions-1.0.3.dist-info/top_level.txt
ipython_suggestions-1.0.3.dist-info/RECORD
