Metadata-Version: 2.4
Name: ipython-suggestions
Version: 1.0.3
Summary: Get suggestions on misspelled names, and do system wide symbol searching.
Home-page: https://github.com/drorspei/ipython-suggestions
Author: Dror Speiser
License: MIT
Classifier: Development Status :: 4 - Beta
Classifier: Framework :: IPython
Classifier: License :: OSI Approved :: MIT License
Classifier: Programming Language :: Python :: 3
Requires-Python: >=2.7.10
License-File: LICENSE.txt
Requires-Dist: ipython>=4.0
Requires-Dist: future; python_version < "3"
Dynamic: author
Dynamic: classifier
Dynamic: description
Dynamic: description-content-type
Dynamic: home-page
Dynamic: license
Dynamic: license-file
Dynamic: requires-dist
Dynamic: requires-python
Dynamic: summary
